prosemirror/__init__.py
prosemirror/py.typed
prosemirror/utils.py
prosemirror/model/__init__.py
prosemirror/model/comparedeep.py
prosemirror/model/content.py
prosemirror/model/diff.py
prosemirror/model/dom.py
prosemirror/model/fragment.py
prosemirror/model/from_dom.py
prosemirror/model/mark.py
prosemirror/model/node.py
prosemirror/model/replace.py
prosemirror/model/resolvedpos.py
prosemirror/model/schema.py
prosemirror/model/to_dom.py
prosemirror/schema/basic/__init__.py
prosemirror/schema/basic/schema_basic.py
prosemirror/schema/list/__init__.py
prosemirror/schema/list/schema_list.py
prosemirror/test_builder/__init__.py
prosemirror/test_builder/build.py
prosemirror/transform/__init__.py
prosemirror/transform/attr_step.py
prosemirror/transform/doc_attr_step.py
prosemirror/transform/map.py
prosemirror/transform/mark.py
prosemirror/transform/mark_step.py
prosemirror/transform/replace.py
prosemirror/transform/replace_step.py
prosemirror/transform/step.py
prosemirror/transform/structure.py
prosemirror/transform/transform.py
prosemirror-0.5.2.dist-info/METADATA
prosemirror-0.5.2.dist-info/WHEEL
prosemirror-0.5.2.dist-info/licenses/LICENSE.md
prosemirror-0.5.2.dist-info/RECORD
