Metadata-Version: 2.4
Name: prosemirror
Version: 0.5.2
Summary: Python implementation of core ProseMirror modules for collaborative editing
Author-email: Samuel Cormier-Iijima <sam@fellow.co>, Shen Li <dustet@gmail.com>
License: BSD-3-Clause
License-File: LICENSE.md
Keywords: collaborative,editing,prosemirror
Requires-Python: >=3.10
Requires-Dist: cssselect>=1.2
Requires-Dist: lxml>=4.9
Requires-Dist: typing-extensions>=4.1
